novum_api/__init__.py
novum_api/api_type.py
novum_api/base_client.py
novum_api/client.py
novum_api-1.0.0a0.dist-info/LICENSE
novum_api-1.0.0a0.dist-info/METADATA
novum_api-1.0.0a0.dist-info/WHEEL
novum_api-1.0.0a0.dist-info/RECORD
