Metadata-Version: 2.1
Name: novum_api
Version: 1.0.0a0
Summary: 
Author: Leonardo
Author-email: l.biz@novum-engineering.com
Requires-Python: >=3.8,<4.0
Classifier: Programming Language :: Python :: 3
Classifier: Programming Language :: Python :: 3.8
Classifier: Programming Language :: Python :: 3.9
Classifier: Programming Language :: Python :: 3.10
Classifier: Programming Language :: Python :: 3.11
Requires-Dist: requests (>=2.28.2,<3.0.0)
